{"Release":"D02B","DocumentType":"MSCONS","TransactionSet":[{"Id":"UNH"},{"Id":"BGM"},{"Id":"DTM","Max":9},{"Id":"CUX","Min":0,"Max":9},{"Id":"RFFLoop1","Min":0,"Max":9,"Loop":[{"Id":"RFF"},{"Id":"DTM","Min":0,"Max":9}]},{"Id":"NADLoop1","Min":0,"Max":99,"Loop":[{"Id":"NAD"},{"Id":"RFFLoop2","Min":0,"Max":9,"Loop":[{"Id":"RFF"},{"Id":"DTM","Min":0,"Max":9}]},{"Id":"CTALoop1","Min":0,"Max":9,"Loop":[{"Id":"CTA"},{"Id":"COM","Min":0,"Max":9}]}]},{"Id":"UNS"},{"Id":"NADLoop2","Max":99999,"Loop":[{"Id":"NAD"},{"Id":"LOCLoop1","Max":99999,"Loop":[{"Id":"LOC"},{"Id":"DTM","Min":0,"Max":9},{"Id":"RFFLoop3","Min":0,"Max":99,"Loop":[{"Id":"RFF"},{"Id":"DTM","Min":0,"Max":9}]},{"Id":"CCILoop1","Min":0,"Max":99,"Loop":[{"Id":"CCI"},{"Id":"DTM","Min":0,"Max":99}]},{"Id":"LINLoop1","Min":0,"Max":99999,"Loop":[{"Id":"LIN"},{"Id":"PIA","Min":0,"Max":9},{"Id":"IMD","Min":0,"Max":9},{"Id":"PRI","Min":0,"Max":9},{"Id":"NAD","Min":0,"Max":9},{"Id":"MOA","Min":0,"Max":9},{"Id":"QTYLoop1","Max":9999,"Loop":[{"Id":"QTY"},{"Id":"DTM","Min":0,"Max":9},{"Id":"STS","Min":0,"Max":9}]},{"Id":"CCILoop2","Min":0,"Max":99,"Loop":[{"Id":"CCI"},{"Id":"MEA","Min":0,"Max":99},{"Id":"DTM","Min":0,"Max":9}]}]}]}]},{"Id":"CNT","Min":0,"Max":99},{"Id":"UNT"}]}
